youcreep/__init__.py
youcreep/browser_agent/__init__.py
youcreep/browser_agent/agent.py
youcreep/browser_agent/url_parser.py
youcreep/browser_agent/modules/__init__.py
youcreep/browser_agent/modules/common_page_handler.py
youcreep/browser_agent/modules/page_handler.py
youcreep/browser_agent/modules/search_page_handler.py
youcreep/browser_agent/modules/short_page_handler.py
youcreep/browser_agent/modules/video_page_handler.py
youcreep/common/__init__.py
youcreep/common/db/__init__.py
youcreep/common/db/sqlite/__init__.py
youcreep/common/db/sqlite/_video_comment.py
youcreep/common/db/sqlite/_video_info.py
youcreep/common/pojo/__init__.py
youcreep/common/pojo/_video_comment.py
youcreep/common/pojo/_video_info.py
youcreep/common/selectors/__init__.py
youcreep/common/selectors/common_sels.py
youcreep/common/selectors/search_result_page.py
youcreep/common/selectors/short_page_sels.py
youcreep/common/selectors/video_page_sels.py
youcreep/crawler/__init__.py
youcreep/crawler/base_crawler.py
youcreep/crawler/video_comment_crawler.py
youcreep/crawler/video_info_crawler.py
youcreep/page_parser/__init__.py
youcreep/page_parser/exception.py
youcreep/page_parser/page_parser.py
youcreep/page_parser/search_page_parser.py
youcreep/page_parser/video_page_parser.py
youcreep-0.1.42.dist-info/METADATA
youcreep-0.1.42.dist-info/WHEEL
youcreep-0.1.42.dist-info/top_level.txt
youcreep-0.1.42.dist-info/RECORD
