Metadata-Version: 2.1
Name: youcreep
Version: 0.1.42
Summary: A powerful, asynchronous web crawler designed specifically for YouTube.
Home-page: https://github.com/stevieflyer/youtube_crawler
Author: Steve Flyer
Author-email: steveflyer7@gmail.com
Requires-Dist: gembox
Requires-Dist: cetino
Requires-Dist: pandas
Requires-Dist: setuptools
Requires-Dist: deprecated
Requires-Dist: playwright
Requires-Dist: wrightyrion
Requires-Dist: beautifulsoup4
